my_functions_beatzaplenty/.gitignore
my_functions_beatzaplenty/README.md
my_functions_beatzaplenty/__init__.py
my_functions_beatzaplenty/check_command_exists.py
my_functions_beatzaplenty/check_outgoing_ports.py
my_functions_beatzaplenty/config.ini
my_functions_beatzaplenty/create-vm.py
my_functions_beatzaplenty/create_config_file.py
my_functions_beatzaplenty/create_ssh_connection.py
my_functions_beatzaplenty/execute_ssh_command.py
my_functions_beatzaplenty/install_required_modules.py
my_functions_beatzaplenty/is_repo_up_to_date.py
my_functions_beatzaplenty/parse_tuple.py
my_functions_beatzaplenty/remote_update.py
my_functions_beatzaplenty/requirements.txt
my_functions_beatzaplenty/resize_linode_instance.py
my_functions_beatzaplenty/run_command.py
my_functions_beatzaplenty/run_updates.py
my_functions_beatzaplenty/update-firewall.py
my_functions_beatzaplenty/update_containers.py
my_functions_beatzaplenty-1.0.13.dist-info/METADATA
my_functions_beatzaplenty-1.0.13.dist-info/WHEEL
my_functions_beatzaplenty-1.0.13.dist-info/licenses/LICENSE
my_functions_beatzaplenty-1.0.13.dist-info/RECORD
