Metadata-Version: 2.3
Name: my_functions_beatzaplenty
Version: 1.0.13
Summary: My Custom functions that I use all the time
Project-URL: Homepage, https://github.com/WayneBennett666/common
Project-URL: Issues, https://github.com/WayneBennett666/common/issues
Author-email: Wayne Bennett <wayne.bennett@live.com>
License-File: LICENSE
Classifier: License :: OSI Approved :: MIT License
Classifier: Operating System :: OS Independent
Classifier: Programming Language :: Python :: 3
Requires-Python: >=3.8
